zengo/__init__.py
zengo/admin.py
zengo/apps.py
zengo/models.py
zengo/service.py
zengo/settings.py
zengo/signals.py
zengo/strings.py
zengo/views.py
zengo/migrations/0001_initial.py
zengo/migrations/0002_attachments.py
zengo/migrations/0003_relax_url_maxlength.py
zengo/migrations/0004_zendeskuser_alias.py
zengo/migrations/0005_ticket_priority.py
zengo/migrations/0006_auto_20200310_1733.py
zengo/migrations/0007_alter_event_remote_ticket_id.py
zengo/migrations/__init__.py
django_zengo-2.0.4.dist-info/LICENSE
django_zengo-2.0.4.dist-info/METADATA
django_zengo-2.0.4.dist-info/WHEEL
django_zengo-2.0.4.dist-info/top_level.txt
django_zengo-2.0.4.dist-info/RECORD
