Metadata-Version: 2.1
Name: django-zengo
Version: 2.0.4
Summary: Integrate Zendesk Support and your Django app
Home-page: https://github.com/lukeburden/django-zengo
Author: Luke Burden
Author-email: lukeburden@gmail.com
License: MIT
Platform: UNKNOWN
Classifier: Development Status :: 5 - Production/Stable
Classifier: Environment :: Web Environment
Classifier: Intended Audience :: Developers
Classifier: License :: OSI Approved :: MIT License
Classifier: Operating System :: OS Independent
Classifier: Programming Language :: Python
Classifier: Programming Language :: Python :: 3
Classifier: Framework :: Django
License-File: LICENSE
Requires-Dist: django (<4,>=2)
Requires-Dist: zenpy (<3,>=2.0.11)
Requires-Dist: django-konst (<3,>=2)
